{
  "_id": "60ef33b427d9471b5bd845ad",
  "id": "leaderboard-2000",
  "date": 1626537237083,
  "date_str": "2021-07-17T15:53:57.083Z",
  "leaderboard": [
    {
      "rank": 1,
      "hid": 274,
      "horse_rating": {
        "cf": "1A",
        "d": "2000",
        "med": 7.52
      },
      "name": "Breathless Edge"
    },
    {
      "rank": 2,
      "hid": 10656,
      "horse_rating": {
        "cf": "1A",
        "d": "2000",
        "med": 8.01
      },
      "name": "Supreme Polarity"
    },
    {
      "rank": 3,
      "hid": 325,
      "horse_rating": {
        "cf": "1A",
        "d": "2000",
        "med": 8.024999999999999
      },
      "name": "Barok"
    },
    {
      "rank": 4,
      "hid": 13769,
      "horse_rating": {
        "cf": "1A",
        "d": "2000",
        "med": 8.205
      },
      "name": "Rendezvous Peak"
    },
    {
      "rank": 5,
      "hid": 13089,
      "horse_rating": {
        "cf": "1A",
        "d": "2000",
        "med": 8.29
      },
      "name": "Wild Thoughts"
    },
    {
      "rank": 6,
      "hid": 1892,
      "horse_rating": {
        "cf": "1A",
        "d": "2000",
        "med": 8.475
      },
      "name": "Ducky Mallon"
    },
    {
      "rank": 7,
      "hid": 18904,
      "horse_rating": {
        "cf": "1A",
        "d": "2000",
        "med": 8.61
      },
      "name": "Vanilla Bean"
    },
    {
      "rank": 8,
      "hid": 362,
      "horse_rating": {
        "cf": "1A",
        "d": "2000",
        "med": 8.66
      },
      "name": "Third Head"
    },
    {
      "rank": 9,
      "hid": 38752,
      "horse_rating": {
        "cf": "1A",
        "d": "2000",
        "med": 8.78
      },
      "name": "You Gonna Work B!tch"
    },
    {
      "rank": 10,
      "hid": 10833,
      "horse_rating": {
        "cf": "1A",
        "d": "2000",
        "med": 8.91
      },
      "name": "Genuine Risk"
    },
    {
      "rank": 11,
      "hid": 372,
      "horse_rating": {
        "cf": "1A",
        "d": "2000",
        "med": 8.934999999999999
      },
      "name": "Phantom Pacer"
    },
    {
      "rank": 12,
      "hid": 296,
      "horse_rating": {
        "cf": "1A",
        "d": "2000",
        "med": 8.97
      },
      "name": "Proud Delight"
    },
    {
      "rank": 13,
      "hid": 23089,
      "horse_rating": {
        "cf": "1A",
        "d": "2000",
        "med": 8.98
      },
      "name": "I Love Pizza"
    },
    {
      "rank": 14,
      "hid": 26122,
      "horse_rating": {
        "cf": "1A",
        "d": "2000",
        "med": 9.02
      },
      "name": "Victorious Taurus"
    },
    {
      "rank": 15,
      "hid": 140,
      "horse_rating": {
        "cf": "1A",
        "d": "2000",
        "med": 9.05
      },
      "name": "Grandeur"
    },
    {
      "rank": 16,
      "hid": 939,
      "horse_rating": {
        "cf": "1A",
        "d": "2000",
        "med": 9.06
      },
      "name": "Insane Hymn"
    },
    {
      "rank": 17,
      "hid": 1529,
      "horse_rating": {
        "cf": "1A",
        "d": "2000",
        "med": 9.07
      },
      "name": "Cutie Cult"
    },
    {
      "rank": 18,
      "hid": 10119,
      "horse_rating": {
        "cf": "1A",
        "d": "2000",
        "med": 9.075
      },
      "name": "Y2k2k"
    },
    {
      "rank": 19,
      "hid": 463,
      "horse_rating": {
        "cf": "1A",
        "d": "2000",
        "med": 9.135000000000002
      },
      "name": "Chromatic Theory"
    },
    {
      "rank": 20,
      "hid": 11146,
      "horse_rating": {
        "cf": "1A",
        "d": "2000",
        "med": 9.14
      },
      "name": "I'm A Ducky On The Edge"
    },
    {
      "rank": 21,
      "hid": 605,
      "horse_rating": {
        "cf": "1A",
        "d": "2000",
        "med": 9.18
      },
      "name": "Figured It Out"
    },
    {
      "rank": 22,
      "hid": 17565,
      "horse_rating": {
        "cf": "1A",
        "d": "2000",
        "med": 9.42
      },
      "name": "Dank"
    },
    {
      "rank": 23,
      "hid": 9663,
      "horse_rating": {
        "cf": "1A",
        "d": "2000",
        "med": 9.434999999999999
      },
      "name": "Pinkman"
    },
    {
      "rank": 24,
      "hid": 27008,
      "horse_rating": {
        "cf": "1A",
        "d": "2000",
        "med": 9.45
      },
      "name": "Charlie Cheval"
    },
    {
      "rank": 25,
      "hid": 12968,
      "horse_rating": {
        "cf": "1A",
        "d": "2000",
        "med": 9.46
      },
      "name": "Star Strider"
    },
    {
      "rank": 26,
      "hid": 23272,
      "horse_rating": {
        "cf": "1A",
        "d": "2000",
        "med": 9.475
      },
      "name": "O'Neill"
    },
    {
      "rank": 27,
      "hid": 26113,
      "horse_rating": {
        "cf": "1A",
        "d": "2000",
        "med": 9.48
      },
      "name": "The Shuffler"
    },
    {
      "rank": 28,
      "hid": 23223,
      "horse_rating": {
        "cf": "1A",
        "d": "2000",
        "med": 9.535
      },
      "name": "Ebony Royal"
    },
    {
      "rank": 29,
      "hid": 15296,
      "horse_rating": {
        "cf": "1A",
        "d": "2000",
        "med": 9.66
      },
      "name": "Steph Curry"
    },
    {
      "rank": 30,
      "hid": 441,
      "horse_rating": {
        "cf": "1A",
        "d": "2000",
        "med": 9.69
      },
      "name": "Bermuda Triangle"
    },
    {
      "rank": 31,
      "hid": 980,
      "horse_rating": {
        "cf": "1A",
        "d": "2000",
        "med": 9.72
      },
      "name": "What Rhymes With Venus"
    },
    {
      "rank": 32,
      "hid": 14867,
      "horse_rating": {
        "cf": "1A",
        "d": "2000",
        "med": 9.74
      },
      "name": "Real Crystal"
    },
    {
      "rank": 33,
      "hid": 7486,
      "horse_rating": {
        "cf": "1A",
        "d": "2000",
        "med": 9.765
      },
      "name": "Chester\t"
    },
    {
      "rank": 34,
      "hid": 7090,
      "horse_rating": {
        "cf": "1A",
        "d": "2000",
        "med": 9.77
      },
      "name": "Bonnie Parker"
    },
    {
      "rank": 35,
      "hid": 24920,
      "horse_rating": {
        "cf": "1A",
        "d": "2000",
        "med": 9.79
      },
      "name": "Perfect Cadence"
    },
    {
      "rank": 36,
      "hid": 22141,
      "horse_rating": {
        "cf": "1A",
        "d": "2000",
        "med": 9.92
      },
      "name": "Royal Acquisition"
    },
    {
      "rank": 37,
      "hid": 12210,
      "horse_rating": {
        "cf": "1A",
        "d": "2000",
        "med": 9.95
      },
      "name": "Spirit of Ecstasy"
    },
    {
      "rank": 38,
      "hid": 1978,
      "horse_rating": {
        "cf": "1A",
        "d": "2000",
        "med": 9.96
      },
      "name": "Bubs Gold"
    },
    {
      "rank": 39,
      "hid": 11967,
      "horse_rating": {
        "cf": "1B",
        "d": "2000",
        "med": 7.92
      },
      "name": "Forever New"
    },
    {
      "rank": 40,
      "hid": 6071,
      "horse_rating": {
        "cf": "1B",
        "d": "2000",
        "med": 8.305
      },
      "name": "Bananarama"
    },
    {
      "rank": 41,
      "hid": 1393,
      "horse_rating": {
        "cf": "1B",
        "d": "2000",
        "med": 8.395
      },
      "name": "Green Eyed Larry"
    },
    {
      "rank": 42,
      "hid": 7759,
      "horse_rating": {
        "cf": "1B",
        "d": "2000",
        "med": 8.47
      },
      "name": "Jordan"
    },
    {
      "rank": 43,
      "hid": 5,
      "horse_rating": {
        "cf": "1B",
        "d": "2000",
        "med": 8.555
      },
      "name": "Something Special"
    },
    {
      "rank": 44,
      "hid": 2009,
      "horse_rating": {
        "cf": "1B",
        "d": "2000",
        "med": 8.68
      },
      "name": "Boom Tune"
    },
    {
      "rank": 45,
      "hid": 12315,
      "horse_rating": {
        "cf": "1B",
        "d": "2000",
        "med": 8.735
      },
      "name": "High Rating"
    },
    {
      "rank": 46,
      "hid": 13405,
      "horse_rating": {
        "cf": "1B",
        "d": "2000",
        "med": 8.75
      },
      "name": "The Publisher"
    },
    {
      "rank": 47,
      "hid": 1446,
      "horse_rating": {
        "cf": "1B",
        "d": "2000",
        "med": 8.97
      },
      "name": "Big And Tall"
    },
    {
      "rank": 48,
      "hid": 7711,
      "horse_rating": {
        "cf": "1B",
        "d": "2000",
        "med": 9.01
      },
      "name": "Sarah Connor"
    },
    {
      "rank": 49,
      "hid": 518,
      "horse_rating": {
        "cf": "1B",
        "d": "2000",
        "med": 9.13
      },
      "name": "Expedition Hero"
    },
    {
      "rank": 50,
      "hid": 264,
      "horse_rating": {
        "cf": "1B",
        "d": "2000",
        "med": 9.14
      },
      "name": "Dank Dank Goose"
    },
    {
      "rank": 51,
      "hid": 26540,
      "horse_rating": {
        "cf": "1B",
        "d": "2000",
        "med": 9.175
      },
      "name": "Loves A Fantasy"
    },
    {
      "rank": 52,
      "hid": 592,
      "horse_rating": {
        "cf": "1B",
        "d": "2000",
        "med": 9.19
      },
      "name": "As Bad As You Remember"
    },
    {
      "rank": 53,
      "hid": 10123,
      "horse_rating": {
        "cf": "1B",
        "d": "2000",
        "med": 9.2
      },
      "name": "Aurora Star"
    },
    {
      "rank": 54,
      "hid": 16396,
      "horse_rating": {
        "cf": "1B",
        "d": "2000",
        "med": 9.23
      },
      "name": "Rest In Peace"
    },
    {
      "rank": 55,
      "hid": 16451,
      "horse_rating": {
        "cf": "1B",
        "d": "2000",
        "med": 9.25
      },
      "name": "Shrimp Bender 69"
    },
    {
      "rank": 56,
      "hid": 26506,
      "horse_rating": {
        "cf": "1B",
        "d": "2000",
        "med": 9.27
      },
      "name": "Born To Finish"
    },
    {
      "rank": 57,
      "hid": 1637,
      "horse_rating": {
        "cf": "1B",
        "d": "2000",
        "med": 9.28
      },
      "name": "Major Major Major"
    },
    {
      "rank": 58,
      "hid": 25088,
      "horse_rating": {
        "cf": "1B",
        "d": "2000",
        "med": 9.28
      },
      "name": "Jhenz"
    },
    {
      "rank": 59,
      "hid": 26574,
      "horse_rating": {
        "cf": "1B",
        "d": "2000",
        "med": 9.285
      },
      "name": "Meat And Two Veg"
    },
    {
      "rank": 60,
      "hid": 20298,
      "horse_rating": {
        "cf": "1B",
        "d": "2000",
        "med": 9.344999999999999
      },
      "name": "Jumbo"
    },
    {
      "rank": 61,
      "hid": 23955,
      "horse_rating": {
        "cf": "1B",
        "d": "2000",
        "med": 9.4
      },
      "name": "Storm Ranger"
    },
    {
      "rank": 62,
      "hid": 12918,
      "horse_rating": {
        "cf": "1B",
        "d": "2000",
        "med": 9.41
      },
      "name": "Unfolded Brilliance"
    },
    {
      "rank": 63,
      "hid": 13389,
      "horse_rating": {
        "cf": "1B",
        "d": "2000",
        "med": 9.455
      },
      "name": "Lost In Space"
    },
    {
      "rank": 64,
      "hid": 3607,
      "horse_rating": {
        "cf": "1B",
        "d": "2000",
        "med": 9.475
      },
      "name": "Saga Bolton"
    },
    {
      "rank": 65,
      "hid": 17766,
      "horse_rating": {
        "cf": "1B",
        "d": "2000",
        "med": 9.49
      },
      "name": "LBJ Goat"
    },
    {
      "rank": 66,
      "hid": 5629,
      "horse_rating": {
        "cf": "1B",
        "d": "2000",
        "med": 9.54
      },
      "name": "Sugar Buzz"
    },
    {
      "rank": 67,
      "hid": 28122,
      "horse_rating": {
        "cf": "1B",
        "d": "2000",
        "med": 9.575
      },
      "name": "Madotti"
    },
    {
      "rank": 68,
      "hid": 1814,
      "horse_rating": {
        "cf": "1B",
        "d": "2000",
        "med": 9.6
      },
      "name": "Enormo"
    },
    {
      "rank": 69,
      "hid": 27007,
      "horse_rating": {
        "cf": "1B",
        "d": "2000",
        "med": 9.64
      },
      "name": "Saffron Sunrise"
    },
    {
      "rank": 70,
      "hid": 8607,
      "horse_rating": {
        "cf": "1B",
        "d": "2000",
        "med": 9.645
      },
      "name": "Slander Unlimited"
    },
    {
      "rank": 71,
      "hid": 22144,
      "horse_rating": {
        "cf": "1B",
        "d": "2000",
        "med": 9.66
      },
      "name": "Rush of Adrenaline"
    },
    {
      "rank": 72,
      "hid": 6423,
      "horse_rating": {
        "cf": "1B",
        "d": "2000",
        "med": 9.73
      },
      "name": "Anmer"
    },
    {
      "rank": 73,
      "hid": 1475,
      "horse_rating": {
        "cf": "1B",
        "d": "2000",
        "med": 9.75
      },
      "name": "So Strong"
    },
    {
      "rank": 74,
      "hid": 13287,
      "horse_rating": {
        "cf": "1B",
        "d": "2000",
        "med": 9.8
      },
      "name": "Ohhh"
    },
    {
      "rank": 75,
      "hid": 17959,
      "horse_rating": {
        "cf": "1B",
        "d": "2000",
        "med": 9.8
      },
      "name": "Moonlight Graham"
    },
    {
      "rank": 76,
      "hid": 13001,
      "horse_rating": {
        "cf": "1B",
        "d": "2000",
        "med": 9.82
      },
      "name": "Big Deal"
    },
    {
      "rank": 77,
      "hid": 12658,
      "horse_rating": {
        "cf": "1B",
        "d": "2000",
        "med": 9.83
      },
      "name": "File Format"
    },
    {
      "rank": 78,
      "hid": 13361,
      "horse_rating": {
        "cf": "1B",
        "d": "2000",
        "med": 9.87
      },
      "name": "Battalion"
    },
    {
      "rank": 79,
      "hid": 12910,
      "horse_rating": {
        "cf": "1B",
        "d": "2000",
        "med": 9.88
      },
      "name": "Zombie Boy"
    },
    {
      "rank": 80,
      "hid": 13012,
      "horse_rating": {
        "cf": "1B",
        "d": "2000",
        "med": 9.899999999999999
      },
      "name": "Open Darkness"
    },
    {
      "rank": 81,
      "hid": 65,
      "horse_rating": {
        "cf": "1B",
        "d": "2000",
        "med": 9.92
      },
      "name": "Ambassador"
    },
    {
      "rank": 82,
      "hid": 20742,
      "horse_rating": {
        "cf": "1B",
        "d": "2000",
        "med": 9.92
      },
      "name": "Giulio Cesare"
    },
    {
      "rank": 83,
      "hid": 1653,
      "horse_rating": {
        "cf": "1B",
        "d": "2000",
        "med": 9.985
      },
      "name": "The One Up"
    },
    {
      "rank": 84,
      "hid": 22873,
      "horse_rating": {
        "cf": "1C",
        "d": "2000",
        "med": 7.84
      },
      "name": "Hypnotic Azalea"
    },
    {
      "rank": 85,
      "hid": 13515,
      "horse_rating": {
        "cf": "1C",
        "d": "2000",
        "med": 8.82
      },
      "name": "Known Solely"
    },
    {
      "rank": 86,
      "hid": 13994,
      "horse_rating": {
        "cf": "1C",
        "d": "2000",
        "med": 8.96
      },
      "name": "Durable"
    },
    {
      "rank": 87,
      "hid": 14822,
      "horse_rating": {
        "cf": "1C",
        "d": "2000",
        "med": 9.06
      },
      "name": "Platinum Spirit"
    },
    {
      "rank": 88,
      "hid": 7820,
      "horse_rating": {
        "cf": "1C",
        "d": "2000",
        "med": 9.4
      },
      "name": "Jedi"
    },
    {
      "rank": 89,
      "hid": 13985,
      "horse_rating": {
        "cf": "1C",
        "d": "2000",
        "med": 9.69
      },
      "name": "Yellow Ochre"
    },
    {
      "rank": 90,
      "hid": 1113,
      "horse_rating": {
        "cf": "1C",
        "d": "2000",
        "med": 9.845
      },
      "name": "Happiness Defined"
    },
    {
      "rank": 91,
      "hid": 7291,
      "horse_rating": {
        "cf": "1C",
        "d": "2000",
        "med": 9.86
      },
      "name": "Candy Cane"
    },
    {
      "rank": 92,
      "hid": 2874,
      "horse_rating": {
        "cf": "1C",
        "d": "2000",
        "med": 9.95
      },
      "name": "Gin Cobbler"
    },
    {
      "rank": 93,
      "hid": 13203,
      "horse_rating": {
        "cf": "1C",
        "d": "2000",
        "med": 9.969999999999999
      },
      "name": "The Kid"
    },
    {
      "rank": 94,
      "hid": 15043,
      "horse_rating": {
        "cf": "2A",
        "d": "2000",
        "med": 7.18
      },
      "name": "Inspector Clouse"
    },
    {
      "rank": 95,
      "hid": 10876,
      "horse_rating": {
        "cf": "2A",
        "d": "2000",
        "med": 7.715
      },
      "name": "Breathless Sequence"
    },
    {
      "rank": 96,
      "hid": 408,
      "horse_rating": {
        "cf": "2A",
        "d": "2000",
        "med": 8.29
      },
      "name": "Backseat Lover"
    },
    {
      "rank": 97,
      "hid": 13110,
      "horse_rating": {
        "cf": "2A",
        "d": "2000",
        "med": 8.34
      },
      "name": "By The Designer"
    },
    {
      "rank": 98,
      "hid": 143,
      "horse_rating": {
        "cf": "2A",
        "d": "2000",
        "med": 8.49
      },
      "name": "Solar"
    },
    {
      "rank": 99,
      "hid": 13030,
      "horse_rating": {
        "cf": "2A",
        "d": "2000",
        "med": 8.54
      },
      "name": "Every Animation"
    },
    {
      "rank": 100,
      "hid": 13967,
      "horse_rating": {
        "cf": "2A",
        "d": "2000",
        "med": 8.55
      },
      "name": "Pineapple Pizza"
    }
  ],
  "leaderboard-dist": "2000"
}